FileMa/FileMa.py
FileMa/__init__.py
FileMa-0.1.5.dist-info/LICENSE
FileMa-0.1.5.dist-info/METADATA
FileMa-0.1.5.dist-info/WHEEL
FileMa-0.1.5.dist-info/top_level.txt
FileMa-0.1.5.dist-info/RECORD
