Metadata-Version: 2.1
Name: FileMa
Version: 0.1.5
Summary: The `FileMa` (File Management)  library provides utilities for file and directory management in Python. It includes functions for creating, removing, renaming, copying files and directories, as well as reading file contents, printing directory structures, and more. The library uses colored terminal output for better visual feedback.
Home-page: https://github.com/ZOUITANE-Ahmed/FileMa.git
Author: Ahmed ZOUITANE
Author-email: zouitane.ahmed02@gmail.com
Classifier: Programming Language :: Python :: 3
Classifier: Programming Language :: Python :: 3.7
Classifier: Programming Language :: Python :: 3.8
Classifier: Programming Language :: Python :: 3.9
Classifier: Programming Language :: Python :: 3.10
Classifier: Programming Language :: Python :: 3.11
Classifier: Programming Language :: Python :: 3.12
Classifier: License :: OSI Approved :: MIT License
Classifier: Operating System :: OS Independent
Requires-Python: >=3.6
License-File: LICENSE
Requires-Dist: colorama >=0.4.4
